urcl/__init__.py
urcl/py.typed
urcl/version.py
urcl/wrapper.cpp
urcl/_init__urcl.py
urcl/_urcl.cpython-312-x86_64-linux-gnu.so
urcl/_urcl.pyi
urcl/urcl.pc
urcl/trampolines/__URCL.hpp
robotpy_urcl-2026.0.0.1.dist-info/METADATA
robotpy_urcl-2026.0.0.1.dist-info/WHEEL
robotpy_urcl-2026.0.0.1.dist-info/entry_points.txt
robotpy_urcl-2026.0.0.1.dist-info/licenses/LICENSE
robotpy_urcl-2026.0.0.1.dist-info/RECORD
