Metadata-Version: 2.4
Name: robotpy-urcl
Version: 2026.0.0.1
Summary: Python wrapper for FRC Team 6328's URCL library
Project-URL: Source code, https://github.com/robotpy/robotpy-urcl
Author-email: RobotPy Development Team <robotpy@googlegroups.com>
License-Expression: MIT
License-File: LICENSE
Requires-Dist: wpilib<2027,>=2026.1.1
